Gfdlws_Sub/__init__.py
Gfdlws_Sub/stream.py
Gfdlws_Sub-0.1.dist-info/METADATA
Gfdlws_Sub-0.1.dist-info/WHEEL
Gfdlws_Sub-0.1.dist-info/top_level.txt
Gfdlws_Sub-0.1.dist-info/RECORD
